hfsynpy/__init__.py
hfsynpy/hfsynpy.py
hfsynpy/hfsynpyusage.py
hfsynpy-0.1.3.dist-info/licenses/LICENSE
hfsynpy-0.1.3.dist-info/METADATA
hfsynpy-0.1.3.dist-info/WHEEL
hfsynpy-0.1.3.dist-info/top_level.txt
hfsynpy-0.1.3.dist-info/RECORD
