Metadata-Version: 2.4
Name: hfsynpy
Version: 0.1.3
Summary: A Python library for synthesis and analysis of high frequency component (currently only microstrip transmission lines), providing accurate models and convenient tools for PCB and RF design.
Home-page: https://github.com/GenerativeAntennaDesign/hfsynpy
Author: Dominik Mair
Author-email: dominik.mair@uibk.ac.at
License: GPL-2.0-or-later
Project-URL: Documentation, https://generativeantennadesign.github.io/hfsynpy/
Project-URL: Source, https://github.com/GenerativeAntennaDesign/hfsynpy
Keywords: microstrip synthesis analysis PCB RF design high frequency transmission line
Classifier: Development Status :: 4 - Beta
Classifier: Intended Audience :: Science/Research
Classifier: Programming Language :: Python :: 3
Classifier: Operating System :: OS Independent
Requires-Python: >=3.7
License-File: LICENSE
Dynamic: author
Dynamic: author-email
Dynamic: classifier
Dynamic: description
Dynamic: description-content-type
Dynamic: home-page
Dynamic: keywords
Dynamic: license
Dynamic: license-file
Dynamic: project-url
Dynamic: requires-python
Dynamic: summary
